fastauth/__init__.py
fastauth/auth_old.py
fastauth/database.py
fastauth/decorators.py
fastauth/endpoints.py
fastauth/middleware.py
fastauth/router.py
fastauth/auth/__init__.py
fastauth/auth/auth_manager.py
fastauth/auth/token_validator.py
fastauth/models/__init__.py
fastauth/models/associations.py
fastauth/models/permission.py
fastauth/models/role.py
fastauth/models/role_permission.py
fastauth/models/user.py
fastauth/models/user_role.py
fastauth/providers/__init__.py
fastauth/providers/auth0_provider.py
fastauth/providers/base.py
fastauth/providers/custom_provider.py
fastauth/providers/factory.py
fastauth/providers/firebase_provider.py
fastauth/providers/jwt_provider.py
fastauth/schemas/__init__.py
fastauth/schemas/associations.py
fastauth/schemas/auth.py
fastauth/schemas/permission.py
fastauth/schemas/role.py
fastauth/schemas/token.py
fastauth/schemas/user.py
fastapi_roles_auth-0.1.2.dist-info/METADATA
fastapi_roles_auth-0.1.2.dist-info/WHEEL
fastapi_roles_auth-0.1.2.dist-info/licenses/LICENSE
fastapi_roles_auth-0.1.2.dist-info/RECORD
