Metadata-Version: 2.4
Name: fastapi-roles-auth
Version: 0.1.2
Summary: A comprehensive FastAPI package for role-based access control with support for multiple auth providers
Author-email: Ton Llucia <tonlls1999@gmail.com>
License: MIT
License-File: LICENSE
Keywords: authentication,authorization,fastapi,permissions,rbac,roles
Classifier: Development Status :: 4 - Beta
Classifier: Framework :: FastAPI
Classifier: Intended Audience :: Developers
Classifier: License :: OSI Approved :: MIT License
Classifier: Operating System :: OS Independent
Classifier: Programming Language :: Python :: 3
Classifier: Programming Language :: Python :: 3.12
Classifier: Topic :: Internet :: WWW/HTTP
Classifier: Topic :: Security
Classifier: Topic :: Software Development :: Libraries :: Python Modules
Requires-Python: >=3.12
Requires-Dist: fastapi>=0.115.12
Requires-Dist: httpx>=0.28.1
Requires-Dist: passlib[bcrypt]>=1.7.4
Requires-Dist: pydantic[email]>=2.11.5
Requires-Dist: python-jose[cryptography]>=3.4.0
Requires-Dist: python-multipart>=0.0.20
Requires-Dist: sqlalchemy>=2.0.41
Provides-Extra: all-databases
Requires-Dist: cx-oracle>=8.3.0; extra == 'all-databases'
Requires-Dist: motor>=3.7.1; extra == 'all-databases'
Requires-Dist: psycopg2-binary>=2.9.10; extra == 'all-databases'
Requires-Dist: pymongo>=4.13.0; extra == 'all-databases'
Requires-Dist: pymysql>=1.1.1; extra == 'all-databases'
Provides-Extra: auth0
Requires-Dist: auth0-python>=4.9.0; extra == 'auth0'
Provides-Extra: dev
Requires-Dist: black>=25.1.0; extra == 'dev'
Requires-Dist: flake8>=7.2.0; extra == 'dev'
Requires-Dist: isort>=6.0.1; extra == 'dev'
Requires-Dist: mypy>=1.15.0; extra == 'dev'
Requires-Dist: pre-commit>=4.2.0; extra == 'dev'
Requires-Dist: pytest-asyncio>=0.26.0; extra == 'dev'
Requires-Dist: pytest-cov>=6.1.1; extra == 'dev'
Requires-Dist: pytest>=8.3.5; extra == 'dev'
Provides-Extra: firebase
Requires-Dist: firebase-admin>=6.8.0; extra == 'firebase'
Provides-Extra: mongodb
Requires-Dist: motor>=3.7.1; extra == 'mongodb'
Requires-Dist: pymongo>=4.13.0; extra == 'mongodb'
Provides-Extra: mysql
Requires-Dist: pymysql>=1.1.1; extra == 'mysql'
Provides-Extra: oracle
Requires-Dist: cx-oracle>=8.3.0; extra == 'oracle'
Provides-Extra: postgres
Requires-Dist: psycopg2-binary>=2.9.10; extra == 'postgres'
Provides-Extra: redis
Requires-Dist: redis>=6.1.0; extra == 'redis'
Provides-Extra: sqlite
